zone4/__init__.py
zone4/zone4manager.py
zone4/zone4output.py
zone4-0.0.1.dist-info/LICENSE.md
zone4-0.0.1.dist-info/METADATA
zone4-0.0.1.dist-info/WHEEL
zone4-0.0.1.dist-info/top_level.txt
zone4-0.0.1.dist-info/RECORD
