Metadata-Version: 2.1
Name: zone4
Version: 0.0.1
Summary: Async library for controlling the Apart Zone4 preamp via serial
Author-email: Sam Smart <me@sam-smart.co.uk>
Project-URL: Homepage, https://github.com/samjsmart/zone4
Keywords: zone4,pre-amp,controller
Classifier: License :: OSI Approved :: MIT License
Classifier: Programming Language :: Python
Classifier: Programming Language :: Python :: 3
Classifier: Topic :: Multimedia :: Sound/Audio
Classifier: Topic :: System :: Hardware
Classifier: Framework :: AsyncIO
Requires-Python: >=3.9
License-File: LICENSE.md
Requires-Dist: asyncio
Requires-Dist: pyserial
Requires-Dist: pyserial-asyncio
